{
    "days": [
        {
            "name": "Friday",
            "hash": "fri",
            "date": "2025-06-13"
        }
    ],

    "rooms": {
    },

    "speakers": {
        "Eric Balkanski" : {
            "name": "Eric Balkanski",
            "href": "/2025/speakers/balkanski/"
        },
        "Hedyeh Beyhaghi" : {
            "name": "Hedyeh Beyhaghi",
            "href": "/2025/speakers/beyhaghi/"
        },
        "Julien Dallot" : {
            "name": "Julien Dallot",
            "href": "/2025/speakers/dallot/"
        },
        "Thodoris Lykouris" : {
            "name": "Thodoris Lykouris",
            "href": "/2025/speakers/lykouris/"
        },
        "Konstantina Mellou" : {
            "name": "Konstantina Mellou",
            "href": "/2025/speakers/mellou/"
        },
        "Poster Authors" : {
            "name": " Poster Authors",
            "href": ""
        },
        "Organizers" : {
            "name": " Organizers",
            "href": ""
        },
        "Sergei Vassilvitskii" : {
            "name": "Sergei Vassilvitskii",
            "href": "/2025/speakers/vassilvitskii/"
        }
    },

    "talks": {
    }
}
